autodatasets/__init__.py
autodatasets-0.0.1.dist-info/LICENSE
autodatasets-0.0.1.dist-info/METADATA
autodatasets-0.0.1.dist-info/WHEEL
autodatasets-0.0.1.dist-info/top_level.txt
autodatasets-0.0.1.dist-info/zip-safe
autodatasets-0.0.1.dist-info/RECORD
